dossier_tools/__init__.py
dossier_tools/cli.py
dossier_tools/logging.py
dossier_tools/py.typed
dossier_tools/search.py
dossier_tools/cache/__init__.py
dossier_tools/cli/__init__.py
dossier_tools/cli/cache.py
dossier_tools/cli/local.py
dossier_tools/cli/registry.py
dossier_tools/core/__init__.py
dossier_tools/core/checksum.py
dossier_tools/core/parser.py
dossier_tools/core/validate.py
dossier_tools/registry/__init__.py
dossier_tools/registry/auth.py
dossier_tools/registry/client.py
dossier_tools/registry/oauth.py
dossier_tools/signing/__init__.py
dossier_tools/signing/base.py
dossier_tools/signing/ed25519.py
dossier_tools/signing/keys.py
dossier_tools/signing/registry.py
dossier_tools/schema/dossier-schema.json
dossier_tools-0.1.10.dist-info/METADATA
dossier_tools-0.1.10.dist-info/WHEEL
dossier_tools-0.1.10.dist-info/entry_points.txt
dossier_tools-0.1.10.dist-info/licenses/LICENSE
dossier_tools-0.1.10.dist-info/RECORD
