Metadata-Version: 2.4
Name: dossier-tools
Version: 0.1.10
Summary: Frontmatter schema, signing, and validation tools for .ds.md workflow files
Project-URL: Homepage, https://github.com/liberioai/dossier-tools
Project-URL: Repository, https://github.com/liberioai/dossier-tools
Project-URL: Issues, https://github.com/liberioai/dossier-tools/issues
Author-email: Liberio AI <team@liberio.ai>
License: MIT License
License-File: LICENSE
Classifier: License :: OSI Approved :: MIT License
Classifier: Operating System :: OS Independent
Classifier: Programming Language :: Python :: 3.10
Classifier: Programming Language :: Python :: 3.11
Classifier: Programming Language :: Python :: 3.12
Requires-Python: >=3.10
Requires-Dist: click>=8.0.0
Requires-Dist: cryptography>=42.0.0
Requires-Dist: httpx>=0.27.0
Requires-Dist: jsonschema>=4.0.0
Requires-Dist: python-frontmatter>=1.0.0
Provides-Extra: dev
Requires-Dist: pre-commit>=3.0.0; extra == 'dev'
Requires-Dist: pytest-cov>=4.0.0; extra == 'dev'
Requires-Dist: pytest>=8.0.0; extra == 'dev'
Requires-Dist: respx>=0.21.0; extra == 'dev'
Requires-Dist: ruff>=0.1.0; extra == 'dev'
